pyEELSMODEL/__init__.py
pyEELSMODEL/api.py
pyEELSMODEL/element_info.hdf5
pyEELSMODEL/components/__init__.py
pyEELSMODEL/components/afterglow.py
pyEELSMODEL/components/constrained_gdoslin.py
pyEELSMODEL/components/exponential.py
pyEELSMODEL/components/fast_background.py
pyEELSMODEL/components/fixedpattern.py
pyEELSMODEL/components/gaussian.py
pyEELSMODEL/components/gdoslin.py
pyEELSMODEL/components/linear.py
pyEELSMODEL/components/linear_background.py
pyEELSMODEL/components/lorentzian.py
pyEELSMODEL/components/lorentzian_sq.py
pyEELSMODEL/components/offset.py
pyEELSMODEL/components/plasmon.py
pyEELSMODEL/components/polynomial.py
pyEELSMODEL/components/powerlaw.py
pyEELSMODEL/components/voigt.py
pyEELSMODEL/components/CLedge/__init__.py
pyEELSMODEL/components/CLedge/coreloss_edge.py
pyEELSMODEL/components/CLedge/dummymodel.py
pyEELSMODEL/components/CLedge/dummymodelcombined.py
pyEELSMODEL/components/CLedge/hydrogen_coreloss_edge.py
pyEELSMODEL/components/CLedge/kohl_coreloss_edge.py
pyEELSMODEL/components/CLedge/kohl_coreloss_edgecombined.py
pyEELSMODEL/components/CLedge/zezhong_coreloss_edge.py
pyEELSMODEL/components/CLedge/zezhong_coreloss_edgecombined.py
pyEELSMODEL/components/MScatter/__init__.py
pyEELSMODEL/components/MScatter/mscatter.py
pyEELSMODEL/components/MScatter/mscatterfft.py
pyEELSMODEL/core/__init__.py
pyEELSMODEL/core/component.py
pyEELSMODEL/core/fitter.py
pyEELSMODEL/core/model.py
pyEELSMODEL/core/multispectrum.py
pyEELSMODEL/core/operator.py
pyEELSMODEL/core/parameter.py
pyEELSMODEL/core/spectrum.py
pyEELSMODEL/database/__init__.py
pyEELSMODEL/database/Segger_Guzzinati_Kohl/__init__.py
pyEELSMODEL/database/Segger_Guzzinati_Kohl/download.py
pyEELSMODEL/database/Zhang/__init__.py
pyEELSMODEL/database/Zhang/download.py
pyEELSMODEL/fitters/__init__.py
pyEELSMODEL/fitters/linear_fitter.py
pyEELSMODEL/fitters/lsqfitter.py
pyEELSMODEL/fitters/minimizefitter.py
pyEELSMODEL/fitters/quadratic_fitter.py
pyEELSMODEL/io_tools/__init__.py
pyeelsmodel-1.0.5.dist-info/licenses/LICENSE
pyeelsmodel-1.0.5.dist-info/METADATA
pyeelsmodel-1.0.5.dist-info/WHEEL
pyeelsmodel-1.0.5.dist-info/top_level.txt
pyeelsmodel-1.0.5.dist-info/RECORD
