Metadata-Version: 2.4
Name: pyEELSMODEL
Version: 1.0.5
Summary: a model based quantification library for electron energy loss spectroscopy
Home-page: https://github.com/joverbee/pyEELSMODEL
Author: Jo Verbeeck and Daen Jannis
Author-email: jo.verbeeck@uantwerpen.be
License: LICENSE.txt
License-File: LICENSE
Requires-Dist: Django>=1.1.1
Requires-Dist: h5py
Requires-Dist: pqdm
Requires-Dist: numpy>=1.20.0
Requires-Dist: matplotlib
Requires-Dist: scipy
Requires-Dist: tqdm
Requires-Dist: fpdf
Requires-Dist: pyqt5
Requires-Dist: pytest
Requires-Dist: jupyter
Requires-Dist: requests
Requires-Dist: quadprog
Dynamic: author
Dynamic: author-email
Dynamic: description
Dynamic: description-content-type
Dynamic: home-page
Dynamic: license
Dynamic: license-file
Dynamic: requires-dist
Dynamic: summary
